requirements.txt
docs/requirements.txt
example/requirements.txt
pytest_mh/__init__.py
pytest_mh/cli.py
pytest_mh/py.typed
pytest_mh/_private/artifacts.py
pytest_mh/_private/data.py
pytest_mh/_private/errors.py
pytest_mh/_private/fixtures.py
pytest_mh/_private/logging.py
pytest_mh/_private/marks.py
pytest_mh/_private/misc.py
pytest_mh/_private/multihost.py
pytest_mh/_private/plugin.py
pytest_mh/_private/topology.py
pytest_mh/_private/topology_controller.py
pytest_mh/_private/types.py
pytest_mh/conn/__init__.py
pytest_mh/conn/container.py
pytest_mh/conn/ssh.py
pytest_mh/utils/__init__.py
pytest_mh/utils/auditd.py
pytest_mh/utils/coredumpd.py
pytest_mh/utils/firewall.py
pytest_mh/utils/fs.py
pytest_mh/utils/hostname.py
pytest_mh/utils/journald.py
pytest_mh/utils/selinux.py
pytest_mh/utils/services.py
pytest_mh/utils/tc.py
pytest_mh-1.0.29.dist-info/METADATA
pytest_mh-1.0.29.dist-info/WHEEL
pytest_mh-1.0.29.dist-info/licenses/LICENSE
pytest_mh-1.0.29.dist-info/RECORD
