Metadata-Version: 2.4
Name: pytest-mh
Version: 1.0.29
Summary: Pytest multihost plugin
Project-URL: Homepage, https://github.com/next-actions/pytest-mh
Project-URL: Bug Tracker, https://github.com/next-actions/pytest-mh/issues
Author-email: Pavel Březina <pbrezina@redhat.com>
License-File: LICENSE
Classifier: License :: OSI Approved :: GNU General Public License v3 (GPLv3)
Classifier: Operating System :: OS Independent
Classifier: Programming Language :: Python :: 3
Requires-Python: >=3.11
Requires-Dist: ansible-pylibssh>=1.3.0
Requires-Dist: colorama
Requires-Dist: pytest
Requires-Dist: pyyaml
